ont/__init__.py
ont/_imdir.py
ont-0.2.0.dist-info/LICENSE.txt
ont-0.2.0.dist-info/METADATA
ont-0.2.0.dist-info/WHEEL
ont-0.2.0.dist-info/top_level.txt
ont-0.2.0.dist-info/RECORD
