Metadata-Version: 2.1
Name: ont
Version: 0.2.0
Summary: Collection of random functions that @jni finds useful
Author-email: Juan Nunez-Iglesias <jni@fastmail.com>
Maintainer-email: Juan Nunez-Iglesias <jni@fastmail.com>
License: Copyright (c) 2023 Juan Nunez-Iglesias
Project-URL: Homepage, https://github.com/jni/ont
Project-URL: Bug Reports, https://github.com/jni/ont/issues
Project-URL: Source, https://github.com/jni/ont
Classifier: Development Status :: 3 - Alpha
Classifier: Intended Audience :: Developers
Classifier: Intended Audience :: Science/Research
Classifier: License :: OSI Approved :: MIT License
Classifier: Programming Language :: Python :: 3
Classifier: Programming Language :: Python :: 3.9
Classifier: Programming Language :: Python :: 3.10
Classifier: Programming Language :: Python :: 3.11
Classifier: Programming Language :: Python :: 3 :: Only
Requires-Python: >=3.9
License-File: LICENSE.txt
Requires-Dist: numpy
Requires-Dist: dask[array]
Requires-Dist: imageio
Provides-Extra: dev
Requires-Dist: check-manifest ; extra == 'dev'
Provides-Extra: test
Requires-Dist: coverage ; extra == 'test'
